korinet/__init__.py
korinet/client.py
korinet/protocol.py
korinet/server.py
korinet-0.0.1a1.dev1.dist-info/licenses/LICENSE
korinet-0.0.1a1.dev1.dist-info/METADATA
korinet-0.0.1a1.dev1.dist-info/WHEEL
korinet-0.0.1a1.dev1.dist-info/top_level.txt
korinet-0.0.1a1.dev1.dist-info/RECORD
