Metadata-Version: 2.4
Name: korinet
Version: 0.0.1a1.dev1
Summary: KoriNet (Korixa Network Protocol) - A lightweight, secure TCP protocol for structured high-level data exchange.
Author: JuanForge
License-Expression: CC-BY-NC-ND-4.0
Project-URL: Homepage, https://github.com/JuanForge/KoriNet
Project-URL: Repository, https://github.com/JuanForge/KoriNet
Project-URL: Issues, https://github.com/JuanForge/KoriNet/issues
Keywords: protocol,tcp,network,cbor,korixa
Classifier: Development Status :: 3 - Alpha
Classifier: Intended Audience :: Developers
Classifier: Topic :: System :: Networking
Classifier: Programming Language :: Python :: 3.11
Classifier: Operating System :: POSIX :: Linux
Requires-Python: >=3.11
License-File: LICENSE
Requires-Dist: cbor2
Dynamic: license-file
